pytestqt/__init__.py
pytestqt/_version.py
pytestqt/exceptions.py
pytestqt/logging.py
pytestqt/modeltest.py
pytestqt/plugin.py
pytestqt/qt_compat.py
pytestqt/qtbot.py
pytestqt/utils.py
pytestqt/wait_signal.py
pytest_qt-4.4.0.dist-info/LICENSE
pytest_qt-4.4.0.dist-info/METADATA
pytest_qt-4.4.0.dist-info/WHEEL
pytest_qt-4.4.0.dist-info/entry_points.txt
pytest_qt-4.4.0.dist-info/top_level.txt
pytest_qt-4.4.0.dist-info/RECORD
